sartoriusb/__init__.py
SartoriUSB-0.2.5.dist-info/LICENSE
SartoriUSB-0.2.5.dist-info/WHEEL
SartoriUSB-0.2.5.dist-info/METADATA
SartoriUSB-0.2.5.dist-info/RECORD
