Metadata-Version: 2.1
Name: SartoriUSB
Version: 0.2.5
Summary: pysartoriusb
Home-page: https://github.com/holgi/sartoriusb
License: Beerware
Author: Holger Frey
Author-email: frey@imtek.de
Requires-Python: >=3.7
Classifier: Development Status :: 4 - Beta
Classifier: Intended Audience :: Developers
Classifier: License :: Freely Distributable
Classifier: Programming Language :: Python :: 3.7
Classifier: Programming Language :: Python :: 3.8
Classifier: Programming Language :: Python :: 3 :: Only
Classifier: Topic :: Scientific/Engineering
Requires-Dist: pyserial >= 3.4
Requires-Dist: black; extra == "dev"
Requires-Dist: flake8; extra == "dev"
Requires-Dist: flake8-comprehensions; extra == "dev"
Requires-Dist: isort; extra == "dev"
Requires-Dist: keyring; extra == "dev"
Requires-Dist: pre-commit; extra == "dev"
Requires-Dist: pytest >=4.0.0; extra == "test"
Requires-Dist: pytest-cov; extra == "test"
Requires-Dist: pytest-mock; extra == "test"
Provides-Extra: dev
Provides-Extra: test
